Metadata-Version: 2.1
Name: telegram-task-bot
Version: 0.1.2
Summary: Library for writing task based telegram bots
Home-page: UNKNOWN
Author: bb4L
Author-email: 39266013+bb4L@users.noreply.github.com
License: UNKNOWN
Project-URL: Source Code, https://github.com/bb4L/telegram-task-bot-pip
Keywords: Telegram,Bot
Platform: UNKNOWN
Classifier: Development Status :: 4 - Beta
Classifier: Intended Audience :: Developers
Classifier: Topic :: Software Development
Classifier: License :: OSI Approved :: GNU Lesser General Public License v3 (LGPLv3)
Classifier: Programming Language :: Python :: 3
Classifier: Programming Language :: Python :: 3.6
Classifier: Programming Language :: Python :: 3.7
Classifier: Programming Language :: Python :: 3.8
